{"level":"info","message":"Processing : POST on : /socket","timeStamp":"2017-12-29T22:45:18.953Z"}
{"level":"info","message":"Server off","timeStamp":"2017-12-29T22:45:18.966Z"}
{"level":"info","message":"Server off","timeStamp":"2017-12-29T22:46:49.833Z"}
{"level":"info","message":"Server off","timeStamp":"2017-12-29T22:47:20.088Z"}
{"level":"info","message":"Server off","timeStamp":"2017-12-29T22:48:35.795Z"}
{"level":"info","message":"Processing : POST on : /socket","timeStamp":"2017-12-29T22:59:21.604Z"}
{"level":"info","message":"Server off","timeStamp":"2017-12-29T22:59:21.618Z"}
{"level":"info","message":"Server is linstening on port 7000","timeStamp":"2017-12-29T23:06:36.316Z"}
{"level":"info","message":"Processing : POST on : /socket","timeStamp":"2017-12-29T23:06:36.340Z"}
{"level":"info","message":"Server is off","timeStamp":"2017-12-29T23:06:36.353Z"}
{"level":"info","message":"Server is linstening on port 7000","timeStamp":"2017-12-29T23:08:24.025Z"}
{"level":"info","message":"Processing : POST on : /socket","timeStamp":"2017-12-29T23:08:24.053Z"}
{"level":"info","message":"Server is off","timeStamp":"2017-12-29T23:08:24.065Z"}
{"level":"info","message":"Server is linstening on port 7000","timeStamp":"2017-12-29T23:14:55.955Z"}
{"level":"info","message":"Processing : POST on : /socket","timeStamp":"2017-12-29T23:14:55.986Z"}
{"level":"info","message":"Server is off","timeStamp":"2017-12-29T23:14:56.010Z"}
{"level":"info","message":"Server is linstening on port 7000","timeStamp":"2017-12-29T23:15:23.562Z"}
{"level":"info","message":"Processing : POST on : /socket","timeStamp":"2017-12-29T23:15:23.594Z"}
{"level":"info","message":"Server is off","timeStamp":"2017-12-29T23:15:23.613Z"}
{"level":"info","message":"Server is linstening on port 7000","timeStamp":"2017-12-29T23:15:33.830Z"}
{"level":"info","message":"Processing : POST on : /socket","timeStamp":"2017-12-29T23:15:33.852Z"}
{"level":"info","message":"Server is off","timeStamp":"2017-12-29T23:15:33.871Z"}
{"level":"info","message":"Server is linstening on port 7000","timeStamp":"2017-12-29T23:15:55.315Z"}
{"level":"info","message":"Processing : POST on : /socket","timeStamp":"2017-12-29T23:15:55.345Z"}
{"level":"info","message":"Server is off","timeStamp":"2017-12-29T23:15:55.358Z"}
{"level":"info","message":"Server is linstening on port 7000","timeStamp":"2017-12-29T23:17:05.957Z"}
{"level":"info","message":"Processing : POST on : /socket","timeStamp":"2017-12-29T23:17:05.994Z"}
{"level":"info","message":"Server is off","timeStamp":"2017-12-29T23:17:06.007Z"}
{"level":"info","message":"Server is linstening on port 7000","timeStamp":"2017-12-29T23:17:51.719Z"}
{"level":"info","message":"Processing : POST on : /socket","timeStamp":"2017-12-29T23:17:51.756Z"}
{"level":"info","message":"Server is off","timeStamp":"2017-12-29T23:17:51.770Z"}
{"level":"info","message":"Server is linstening on port 7000","timeStamp":"2017-12-29T23:18:44.309Z"}
{"level":"info","message":"Processing : POST on : /socket","timeStamp":"2017-12-29T23:18:44.342Z"}
{"level":"info","message":"Server is off","timeStamp":"2017-12-29T23:18:44.406Z"}
{"level":"info","message":"Server is linstening on port 7000","timeStamp":"2017-12-29T23:27:36.863Z"}
{"level":"info","message":"Processing : POST on : /socket","timeStamp":"2017-12-29T23:27:36.899Z"}
{"level":"info","message":"Server is off","timeStamp":"2017-12-29T23:27:36.926Z"}
{"level":"info","message":"Server is linstening on port 7000","timeStamp":"2017-12-29T23:27:44.265Z"}
{"level":"info","message":"Processing : POST on : /socket","timeStamp":"2017-12-29T23:27:44.302Z"}
{"level":"info","message":"Processing : POST on : /socket","timeStamp":"2017-12-29T23:27:44.330Z"}
{"level":"info","message":"Server is off","timeStamp":"2017-12-29T23:27:44.333Z"}
{"level":"info","message":"Server is linstening on port 7000","timeStamp":"2017-12-29T23:28:36.890Z"}
{"level":"info","message":"Processing : POST on : /socket","timeStamp":"2017-12-29T23:28:36.925Z"}
{"level":"info","message":"Server is off","timeStamp":"2017-12-29T23:28:36.953Z"}
{"level":"info","message":"Server is linstening on port 7000","timeStamp":"2017-12-29T23:29:02.216Z"}
{"level":"info","message":"Processing : POST on : /socket","timeStamp":"2017-12-29T23:29:02.252Z"}
{"level":"info","message":"Server is off","timeStamp":"2017-12-29T23:29:02.280Z"}
{"level":"info","message":"Server is linstening on port 7000","timeStamp":"2017-12-29T23:29:29.366Z"}
{"level":"info","message":"Processing : POST on : /socket","timeStamp":"2017-12-29T23:29:29.403Z"}
{"level":"info","message":"Processing : POST on : /socket","timeStamp":"2017-12-29T23:29:29.431Z"}
{"level":"info","message":"Processing : GET on : /socket","timeStamp":"2017-12-29T23:29:29.435Z"}
{"level":"info","message":"Server is off","timeStamp":"2017-12-29T23:29:29.445Z"}
{"level":"info","message":"Server is linstening on port 7000","timeStamp":"2017-12-29T23:30:29.238Z"}
{"level":"info","message":"Processing : POST on : /socket","timeStamp":"2017-12-29T23:30:29.274Z"}
{"level":"info","message":"Processing : POST on : /socket","timeStamp":"2017-12-29T23:30:29.302Z"}
{"level":"info","message":"Processing : GET on : /socket","timeStamp":"2017-12-29T23:30:29.305Z"}
{"level":"info","message":"Server is off","timeStamp":"2017-12-29T23:30:29.316Z"}
{"level":"info","message":"Server is linstening on port 7000","timeStamp":"2017-12-29T23:31:25.937Z"}
{"level":"info","message":"Processing : POST on : /socket","timeStamp":"2017-12-29T23:31:25.954Z"}
{"level":"info","message":"Processing : POST on : /socket","timeStamp":"2017-12-29T23:31:25.983Z"}
{"level":"info","message":"Processing : GET on : /socket","timeStamp":"2017-12-29T23:31:25.987Z"}
{"level":"info","message":"Server is off","timeStamp":"2017-12-29T23:31:25.997Z"}
{"level":"info","message":"Server is linstening on port 7000","timeStamp":"2017-12-29T23:31:44.262Z"}
{"level":"info","message":"Processing : POST on : /socket","timeStamp":"2017-12-29T23:31:44.288Z"}
{"level":"info","message":"Processing : POST on : /socket","timeStamp":"2017-12-29T23:31:44.318Z"}
{"level":"info","message":"Processing : GET on : /socket","timeStamp":"2017-12-29T23:31:44.321Z"}
{"level":"info","message":"Server is off","timeStamp":"2017-12-29T23:31:44.333Z"}
{"level":"info","message":"Server is linstening on port 7000","timeStamp":"2017-12-29T23:32:36.689Z"}
{"level":"info","message":"Processing : POST on : /socket","timeStamp":"2017-12-29T23:32:36.725Z"}
{"level":"info","message":"Processing : POST on : /socket","timeStamp":"2017-12-29T23:32:36.753Z"}
{"level":"info","message":"Processing : GET on : /socket","timeStamp":"2017-12-29T23:32:36.756Z"}
{"level":"info","message":"Server is off","timeStamp":"2017-12-29T23:32:36.767Z"}
{"level":"info","message":"Server is linstening on port 7000","timeStamp":"2017-12-29T23:32:57.942Z"}
{"level":"info","message":"Processing : POST on : /socket","timeStamp":"2017-12-29T23:32:57.977Z"}
{"level":"info","message":"Processing : POST on : /socket","timeStamp":"2017-12-29T23:32:58.005Z"}
{"level":"info","message":"Processing : GET on : /socket","timeStamp":"2017-12-29T23:32:58.008Z"}
{"level":"info","message":"Server is off","timeStamp":"2017-12-29T23:32:58.018Z"}
{"level":"info","message":"Server is linstening on port 7000","timeStamp":"2017-12-29T23:35:43.046Z"}
{"level":"info","message":"Processing : POST on : /socket","timeStamp":"2017-12-29T23:35:43.065Z"}
{"level":"info","message":"Processing : POST on : /socket","timeStamp":"2017-12-29T23:35:43.613Z"}
{"level":"info","message":"Processing : GET on : /socket","timeStamp":"2017-12-29T23:35:43.694Z"}
{"level":"info","message":"Server is off","timeStamp":"2017-12-29T23:35:43.809Z"}
{"level":"info","message":"Server is linstening on port 7000","timeStamp":"2017-12-30T00:04:03.471Z"}
{"level":"info","message":"Processing : POST on : /socket","timeStamp":"2017-12-30T00:04:03.500Z"}
{"level":"info","message":"Processing : POST on : /socket","timeStamp":"2017-12-30T00:04:04.022Z"}
{"level":"info","message":"Processing : GET on : /socket","timeStamp":"2017-12-30T00:04:04.099Z"}
{"level":"info","message":"Server is off","timeStamp":"2017-12-30T00:04:04.202Z"}
{"level":"info","message":"Server is linstening on port 7000","timeStamp":"2017-12-30T00:04:23.127Z"}
{"level":"info","message":"Processing : POST on : /socket","timeStamp":"2017-12-30T00:04:23.158Z"}
{"level":"info","message":"Processing : POST on : /socket","timeStamp":"2017-12-30T00:04:23.655Z"}
{"level":"info","message":"Processing : GET on : /socket","timeStamp":"2017-12-30T00:04:23.735Z"}
{"level":"info","message":"Server is off","timeStamp":"2017-12-30T00:04:23.839Z"}
{"level":"info","message":"Server is linstening on port 7000","timeStamp":"2017-12-30T00:05:02.328Z"}
{"level":"info","message":"Processing : POST on : /socket","timeStamp":"2017-12-30T00:05:02.357Z"}
{"level":"info","message":"Processing : POST on : /socket","timeStamp":"2017-12-30T00:05:02.866Z"}
{"level":"info","message":"Processing : GET on : /socket","timeStamp":"2017-12-30T00:05:02.946Z"}
{"level":"info","message":"Server is off","timeStamp":"2017-12-30T00:05:03.050Z"}
{"level":"info","message":"Server is linstening on port 7000","timeStamp":"2017-12-30T00:05:10.121Z"}
{"level":"info","message":"Processing : POST on : /socket","timeStamp":"2017-12-30T00:05:10.134Z"}
{"level":"info","message":"Processing : POST on : /socket","timeStamp":"2017-12-30T00:05:10.631Z"}
{"level":"info","message":"Processing : GET on : /socket","timeStamp":"2017-12-30T00:05:10.715Z"}
{"level":"info","message":"Server is off","timeStamp":"2017-12-30T00:05:10.820Z"}
{"level":"info","message":"Server is linstening on port 7000","timeStamp":"2017-12-30T00:05:13.712Z"}
{"level":"info","message":"Processing : POST on : /socket","timeStamp":"2017-12-30T00:05:13.737Z"}
{"level":"info","message":"Processing : POST on : /socket","timeStamp":"2017-12-30T00:05:14.230Z"}
{"level":"info","message":"Processing : GET on : /socket","timeStamp":"2017-12-30T00:05:14.308Z"}
{"level":"info","message":"Server is off","timeStamp":"2017-12-30T00:05:14.396Z"}
{"level":"info","message":"Server is linstening on port 7000","timeStamp":"2017-12-30T00:05:26.803Z"}
{"level":"info","message":"Processing : POST on : /socket","timeStamp":"2017-12-30T00:05:26.834Z"}
{"level":"info","message":"Processing : POST on : /socket","timeStamp":"2017-12-30T00:05:27.347Z"}
{"level":"info","message":"Processing : GET on : /socket","timeStamp":"2017-12-30T00:05:27.427Z"}
{"level":"info","message":"Server is off","timeStamp":"2017-12-30T00:05:27.530Z"}
{"level":"info","message":"Server is linstening on port 7000","timeStamp":"2017-12-30T00:06:05.355Z"}
{"level":"info","message":"Processing : POST on : /socket","timeStamp":"2017-12-30T00:06:05.384Z"}
{"level":"info","message":"Processing : POST on : /socket","timeStamp":"2017-12-30T00:06:06.351Z"}
{"level":"info","message":"Processing : GET on : /socket","timeStamp":"2017-12-30T00:06:06.431Z"}
{"level":"info","message":"Server is off","timeStamp":"2017-12-30T00:06:06.543Z"}
{"level":"info","message":"Server is linstening on port 7000","timeStamp":"2017-12-30T00:07:14.936Z"}
{"level":"info","message":"Processing : POST on : /socket","timeStamp":"2017-12-30T00:07:14.967Z"}
{"level":"info","message":"Processing : POST on : /socket","timeStamp":"2017-12-30T00:07:15.558Z"}
{"level":"info","message":"Processing : GET on : /socket","timeStamp":"2017-12-30T00:07:15.639Z"}
{"level":"info","message":"Server is off","timeStamp":"2017-12-30T00:07:15.815Z"}
{"level":"info","message":"Server is linstening on port 7000","timeStamp":"2017-12-30T00:08:33.597Z"}
{"level":"info","message":"Processing : POST on : /socket","timeStamp":"2017-12-30T00:08:33.626Z"}
{"level":"info","message":"Processing : POST on : /socket","timeStamp":"2017-12-30T00:08:34.200Z"}
{"level":"info","message":"Processing : GET on : /socket","timeStamp":"2017-12-30T00:08:34.276Z"}
{"level":"info","message":"Server is off","timeStamp":"2017-12-30T00:08:34.442Z"}
{"level":"info","message":"Server is linstening on port 7000","timeStamp":"2017-12-31T21:41:40.899Z"}
{"level":"info","message":"Processing : POST on : /socket","timeStamp":"2017-12-31T21:41:40.938Z"}
{"level":"info","message":"Processing : POST on : /socket","timeStamp":"2017-12-31T21:41:41.525Z"}
{"level":"info","message":"Processing : GET on : /socket","timeStamp":"2017-12-31T21:41:41.599Z"}
{"level":"info","message":"Server is off","timeStamp":"2017-12-31T21:41:41.766Z"}
{"level":"info","message":"Server is linstening on port 7000","timeStamp":"2017-12-31T21:41:42.178Z"}
{"level":"info","message":"Processing : POST on : /block","timeStamp":"2017-12-31T21:41:42.219Z"}
{"level":"info","message":"Returning a 404 from the catch all route.","timeStamp":"2017-12-31T21:41:42.219Z"}
{"level":"info","message":"Server is off","timeStamp":"2017-12-31T21:41:42.222Z"}
{"level":"info","message":"Server is linstening on port 7000","timeStamp":"2017-12-31T21:43:52.425Z"}
{"level":"info","message":"Processing : POST on : /block","timeStamp":"2017-12-31T21:43:52.464Z"}
{"level":"info","message":"Returning a 404 from the catch all route.","timeStamp":"2017-12-31T21:43:52.465Z"}
{"level":"info","message":"Server is off","timeStamp":"2017-12-31T21:43:52.470Z"}
{"level":"info","message":"Server is linstening on port 7000","timeStamp":"2017-12-31T21:43:53.005Z"}
{"level":"info","message":"Processing : POST on : /socket","timeStamp":"2017-12-31T21:43:53.007Z"}
{"level":"info","message":"Processing : POST on : /socket","timeStamp":"2017-12-31T21:43:53.552Z"}
{"level":"info","message":"Processing : GET on : /socket","timeStamp":"2017-12-31T21:43:53.643Z"}
{"level":"info","message":"Server is off","timeStamp":"2017-12-31T21:43:53.812Z"}
{"level":"info","message":"Server is linstening on port 7000","timeStamp":"2017-12-31T21:44:06.809Z"}
{"level":"info","message":"Processing : POST on : /block","timeStamp":"2017-12-31T21:44:06.850Z"}
{"level":"info","message":"Returning a 404 from the catch all route.","timeStamp":"2017-12-31T21:44:06.850Z"}
{"level":"info","message":"Server is off","timeStamp":"2017-12-31T21:44:06.856Z"}
{"level":"info","message":"Server is linstening on port 7000","timeStamp":"2017-12-31T21:45:36.743Z"}
{"level":"info","message":"Processing : POST on : /block","timeStamp":"2017-12-31T21:45:36.786Z"}
{"level":"info","message":"Returning a 404 from the catch all route.","timeStamp":"2017-12-31T21:45:36.786Z"}
{"level":"info","message":"Server is off","timeStamp":"2017-12-31T21:45:36.792Z"}
{"level":"info","message":"Server is linstening on port 7000","timeStamp":"2017-12-31T21:46:28.043Z"}
{"level":"info","message":"Server is off","timeStamp":"2017-12-31T21:46:28.046Z"}
{"level":"info","message":"Server is linstening on port 7000","timeStamp":"2017-12-31T21:46:44.133Z"}
{"level":"info","message":"Processing : POST on : /block","timeStamp":"2017-12-31T21:46:44.153Z"}
{"level":"info","message":"Returning a 404 from the catch all route.","timeStamp":"2017-12-31T21:46:44.154Z"}
{"level":"info","message":"Server is off","timeStamp":"2017-12-31T21:46:44.159Z"}
{"level":"info","message":"Server is linstening on port 7000","timeStamp":"2017-12-31T21:47:43.603Z"}
{"level":"info","message":"Processing : POST on : /block","timeStamp":"2017-12-31T21:47:43.614Z"}
{"level":"info","message":"Server is off","timeStamp":"2017-12-31T21:47:43.629Z"}
{"level":"info","message":"Server is linstening on port 7000","timeStamp":"2017-12-31T21:48:24.474Z"}
{"level":"info","message":"Processing : POST on : /block","timeStamp":"2017-12-31T21:48:24.486Z"}
{"level":"info","message":"Server is off","timeStamp":"2017-12-31T21:48:24.502Z"}
{"level":"info","message":"Server is linstening on port 7000","timeStamp":"2017-12-31T21:52:57.552Z"}
{"level":"info","message":"Processing : POST on : /block","timeStamp":"2017-12-31T21:52:57.566Z"}
{"level":"info","message":"Server is off","timeStamp":"2017-12-31T21:52:57.581Z"}
{"level":"info","message":"Server is linstening on port 7000","timeStamp":"2017-12-31T21:53:19.303Z"}
{"level":"info","message":"Processing : POST on : /block","timeStamp":"2017-12-31T21:53:19.323Z"}
{"level":"info","message":"Server is off","timeStamp":"2017-12-31T21:53:19.338Z"}
{"level":"info","message":"Server is linstening on port 7000","timeStamp":"2017-12-31T21:54:05.784Z"}
{"level":"info","message":"Processing : POST on : /block","timeStamp":"2017-12-31T21:54:05.804Z"}
{"level":"info","message":"Server is off","timeStamp":"2017-12-31T21:54:05.819Z"}
{"level":"info","message":"Server is linstening on port 7000","timeStamp":"2017-12-31T21:56:49.796Z"}
{"level":"info","message":"Processing : POST on : /block","timeStamp":"2017-12-31T21:56:49.808Z"}
{"level":"info","message":"Server is off","timeStamp":"2017-12-31T21:56:49.827Z"}
{"level":"info","message":"Server is linstening on port 7000","timeStamp":"2017-12-31T21:57:42.660Z"}
{"level":"info","message":"Processing : POST on : /block","timeStamp":"2017-12-31T21:57:42.671Z"}
{"level":"info","message":"Server is off","timeStamp":"2017-12-31T21:57:42.691Z"}
{"level":"info","message":"Server is linstening on port 7000","timeStamp":"2017-12-31T21:58:21.785Z"}
{"level":"info","message":"Processing : POST on : /block","timeStamp":"2017-12-31T21:58:21.795Z"}
{"level":"info","message":"Server is off","timeStamp":"2017-12-31T21:58:21.809Z"}
{"level":"info","message":"Server is linstening on port 7000","timeStamp":"2017-12-31T21:59:40.397Z"}
{"level":"info","message":"Processing : POST on : /block","timeStamp":"2017-12-31T21:59:40.410Z"}
{"level":"info","message":"Server is off","timeStamp":"2017-12-31T21:59:40.424Z"}
{"level":"info","message":"Server is linstening on port 7000","timeStamp":"2017-12-31T22:01:42.708Z"}
{"level":"info","message":"Processing : POST on : /block","timeStamp":"2017-12-31T22:01:42.720Z"}
{"level":"info","message":"Server is off","timeStamp":"2017-12-31T22:01:42.735Z"}
{"level":"info","message":"Server is linstening on port 7000","timeStamp":"2017-12-31T22:03:00.003Z"}
{"level":"info","message":"Processing : POST on : /block","timeStamp":"2017-12-31T22:03:00.015Z"}
{"level":"info","message":"Server is off","timeStamp":"2017-12-31T22:03:00.036Z"}
{"level":"info","message":"Server is linstening on port 7000","timeStamp":"2017-12-31T22:03:20.117Z"}
{"level":"info","message":"Processing : POST on : /block","timeStamp":"2017-12-31T22:03:20.128Z"}
{"level":"info","message":"Server is off","timeStamp":"2017-12-31T22:03:20.148Z"}
{"level":"info","message":"Server is linstening on port 7000","timeStamp":"2017-12-31T22:04:03.669Z"}
{"level":"info","message":"Processing : POST on : /block","timeStamp":"2017-12-31T22:04:03.682Z"}
{"level":"info","message":"Server is off","timeStamp":"2017-12-31T22:04:03.698Z"}
{"level":"info","message":"Server is linstening on port 7000","timeStamp":"2017-12-31T22:10:10.037Z"}
{"level":"info","message":"Processing : POST on : /block","timeStamp":"2017-12-31T22:10:10.047Z"}
{"level":"info","message":"Server is off","timeStamp":"2017-12-31T22:10:10.061Z"}
{"level":"info","message":"Server is linstening on port 7000","timeStamp":"2017-12-31T22:10:57.687Z"}
{"level":"info","message":"Processing : POST on : /block","timeStamp":"2017-12-31T22:10:57.701Z"}
{"level":"info","message":"Server is off","timeStamp":"2017-12-31T22:10:57.717Z"}
{"level":"info","message":"Server is linstening on port 7000","timeStamp":"2017-12-31T22:11:56.864Z"}
{"level":"info","message":"Processing : POST on : /block","timeStamp":"2017-12-31T22:11:56.878Z"}
{"level":"info","message":"Server is off","timeStamp":"2017-12-31T22:11:56.900Z"}
{"level":"info","message":"Server is linstening on port 7000","timeStamp":"2017-12-31T22:12:25.988Z"}
{"level":"info","message":"Processing : POST on : /block","timeStamp":"2017-12-31T22:12:25.999Z"}
{"level":"info","message":"Server is off","timeStamp":"2017-12-31T22:12:26.007Z"}
{"level":"info","message":"Server is linstening on port 7000","timeStamp":"2017-12-31T22:12:42.348Z"}
{"level":"info","message":"Processing : POST on : /block","timeStamp":"2017-12-31T22:12:42.361Z"}
{"level":"info","message":"Server is off","timeStamp":"2017-12-31T22:12:42.371Z"}
{"level":"info","message":"Server is linstening on port 7000","timeStamp":"2017-12-31T22:12:54.718Z"}
{"level":"info","message":"Processing : POST on : /block","timeStamp":"2017-12-31T22:12:54.729Z"}
{"level":"info","message":"Server is off","timeStamp":"2017-12-31T22:12:54.745Z"}
{"level":"info","message":"Server is linstening on port 7000","timeStamp":"2017-12-31T22:13:18.372Z"}
{"level":"info","message":"Processing : POST on : /block","timeStamp":"2017-12-31T22:13:18.386Z"}
{"level":"info","message":"Server is off","timeStamp":"2017-12-31T22:13:18.409Z"}
{"level":"info","message":"Server is linstening on port 7000","timeStamp":"2017-12-31T22:13:47.757Z"}
{"level":"info","message":"Processing : POST on : /block","timeStamp":"2017-12-31T22:13:47.768Z"}
{"level":"info","message":"Server is off","timeStamp":"2017-12-31T22:13:47.784Z"}
{"level":"info","message":"Server is linstening on port 7000","timeStamp":"2017-12-31T22:14:31.771Z"}
{"level":"info","message":"Processing : POST on : /block","timeStamp":"2017-12-31T22:14:31.781Z"}
{"level":"info","message":"Server is off","timeStamp":"2017-12-31T22:14:31.796Z"}
{"level":"info","message":"Server is linstening on port 7000","timeStamp":"2017-12-31T22:15:08.748Z"}
{"level":"info","message":"Processing : POST on : /block","timeStamp":"2017-12-31T22:15:08.761Z"}
{"level":"info","message":"Server is off","timeStamp":"2017-12-31T22:15:08.775Z"}
{"level":"info","message":"Server is linstening on port 7000","timeStamp":"2017-12-31T22:17:38.451Z"}
{"level":"info","message":"Processing : POST on : /block","timeStamp":"2017-12-31T22:17:38.462Z"}
{"level":"info","message":"Server is off","timeStamp":"2017-12-31T22:17:38.481Z"}
{"level":"info","message":"Server is linstening on port 7000","timeStamp":"2017-12-31T22:17:51.693Z"}
{"level":"info","message":"Processing : POST on : /block","timeStamp":"2017-12-31T22:17:51.737Z"}
{"level":"info","message":"Server is off","timeStamp":"2017-12-31T22:17:51.757Z"}
{"level":"info","message":"Server is linstening on port 7000","timeStamp":"2017-12-31T22:21:03.364Z"}
{"level":"info","message":"Processing : POST on : /block","timeStamp":"2017-12-31T22:21:03.374Z"}
{"level":"info","message":"Server is off","timeStamp":"2017-12-31T22:21:03.389Z"}
{"level":"info","message":"Server is linstening on port 7000","timeStamp":"2017-12-31T22:24:07.469Z"}
{"level":"info","message":"Processing : POST on : /block","timeStamp":"2017-12-31T22:24:07.479Z"}
{"level":"info","message":"Server is off","timeStamp":"2017-12-31T22:24:07.494Z"}
{"level":"info","message":"Server is linstening on port 7000","timeStamp":"2017-12-31T22:24:37.363Z"}
{"level":"info","message":"Processing : POST on : /block","timeStamp":"2017-12-31T22:24:37.373Z"}
{"level":"info","message":"Server is off","timeStamp":"2017-12-31T22:24:37.388Z"}
{"level":"info","message":"Server is linstening on port 7000","timeStamp":"2017-12-31T22:25:26.475Z"}
{"level":"info","message":"Processing : POST on : /block","timeStamp":"2017-12-31T22:25:26.486Z"}
{"level":"info","message":"Server is off","timeStamp":"2017-12-31T22:25:26.506Z"}
{"level":"info","message":"Server is linstening on port 7000","timeStamp":"2017-12-31T22:25:48.821Z"}
{"level":"info","message":"Processing : POST on : /block","timeStamp":"2017-12-31T22:25:48.832Z"}
{"level":"info","message":"Server is off","timeStamp":"2017-12-31T22:25:48.848Z"}
{"level":"info","message":"Server is linstening on port 7000","timeStamp":"2017-12-31T22:27:44.303Z"}
{"level":"info","message":"Processing : POST on : /block","timeStamp":"2017-12-31T22:27:44.314Z"}
{"level":"info","message":"Server is off","timeStamp":"2017-12-31T22:27:44.329Z"}
{"level":"info","message":"Server is linstening on port 7000","timeStamp":"2017-12-31T22:28:16.977Z"}
{"level":"info","message":"Processing : POST on : /block","timeStamp":"2017-12-31T22:28:16.989Z"}
{"level":"info","message":"Server is off","timeStamp":"2017-12-31T22:28:17.005Z"}
{"level":"info","message":"Server is linstening on port 7000","timeStamp":"2017-12-31T22:30:41.646Z"}
{"level":"info","message":"Processing : POST on : /block","timeStamp":"2017-12-31T22:30:41.656Z"}
{"level":"info","message":"Server is off","timeStamp":"2017-12-31T22:30:41.673Z"}
{"level":"info","message":"Server is linstening on port 7000","timeStamp":"2017-12-31T22:31:20.498Z"}
{"level":"info","message":"Processing : POST on : /block","timeStamp":"2017-12-31T22:31:20.509Z"}
{"level":"info","message":"Server is off","timeStamp":"2017-12-31T22:31:20.523Z"}
{"level":"info","message":"Server is linstening on port 7000","timeStamp":"2017-12-31T22:34:41.780Z"}
{"level":"info","message":"Processing : POST on : /block","timeStamp":"2017-12-31T22:34:41.791Z"}
{"level":"info","message":"Server is linstening on port 7000","timeStamp":"2017-12-31T22:36:11.360Z"}
{"level":"info","message":"Processing : POST on : /block","timeStamp":"2017-12-31T22:36:11.371Z"}
{"level":"info","message":"Server is off","timeStamp":"2017-12-31T22:36:11.392Z"}
{"level":"info","message":"Server is linstening on port 7000","timeStamp":"2017-12-31T22:37:05.719Z"}
{"level":"info","message":"Processing : POST on : /block","timeStamp":"2017-12-31T22:37:05.731Z"}
{"level":"info","message":"Server is off","timeStamp":"2017-12-31T22:37:05.749Z"}
{"level":"info","message":"Server is linstening on port 7000","timeStamp":"2017-12-31T22:38:13.472Z"}
{"level":"info","message":"Processing : POST on : /block","timeStamp":"2017-12-31T22:38:13.487Z"}
{"level":"info","message":"Server is off","timeStamp":"2017-12-31T22:38:13.508Z"}
{"level":"info","message":"Server is linstening on port 7000","timeStamp":"2017-12-31T22:39:27.688Z"}
{"level":"info","message":"Processing : POST on : /block","timeStamp":"2017-12-31T22:39:27.700Z"}
{"level":"info","message":"Server is linstening on port 7000","timeStamp":"2017-12-31T22:41:04.121Z"}
{"level":"info","message":"Processing : POST on : /block","timeStamp":"2017-12-31T22:41:04.139Z"}
{"level":"info","message":"Server is linstening on port 7000","timeStamp":"2017-12-31T22:43:29.855Z"}
{"level":"info","message":"Processing : POST on : /block","timeStamp":"2017-12-31T22:43:29.865Z"}
{"level":"info","message":"Server is linstening on port 7000","timeStamp":"2017-12-31T22:45:16.398Z"}
{"level":"info","message":"Processing : POST on : /block","timeStamp":"2017-12-31T22:45:16.408Z"}
{"level":"info","message":"Server is off","timeStamp":"2017-12-31T22:47:16.499Z"}
{"level":"info","message":"Server is linstening on port 7000","timeStamp":"2017-12-31T22:48:36.879Z"}
{"level":"info","message":"Processing : POST on : /block","timeStamp":"2017-12-31T22:48:36.890Z"}
{"level":"info","message":"Server is linstening on port 7000","timeStamp":"2017-12-31T22:49:45.011Z"}
{"level":"info","message":"Processing : POST on : /block","timeStamp":"2017-12-31T22:49:45.023Z"}
{"level":"info","message":"Server is off","timeStamp":"2017-12-31T22:51:45.036Z"}
{"level":"info","message":"Server is linstening on port 7000","timeStamp":"2017-12-31T22:54:47.998Z"}
{"level":"info","message":"Processing : POST on : /block","timeStamp":"2017-12-31T22:54:48.009Z"}
{"level":"info","message":"Server is off","timeStamp":"2017-12-31T22:56:48.097Z"}
{"level":"info","message":"Server is linstening on port 7000","timeStamp":"2018-01-02T18:06:59.062Z"}
{"level":"info","message":"Processing : POST on : /block","timeStamp":"2018-01-02T18:06:59.076Z"}
{"level":"info","message":"Server is off","timeStamp":"2018-01-02T18:06:59.102Z"}
{"level":"info","message":"Server is linstening on port 7000","timeStamp":"2018-01-02T18:08:02.058Z"}
{"level":"info","message":"Processing : POST on : /block","timeStamp":"2018-01-02T18:08:02.073Z"}
{"level":"info","message":"Server is off","timeStamp":"2018-01-02T18:08:02.097Z"}
{"level":"info","message":"Server is linstening on port 7000","timeStamp":"2018-01-02T18:08:33.527Z"}
{"level":"info","message":"Processing : POST on : /block","timeStamp":"2018-01-02T18:08:33.542Z"}
{"level":"info","message":"Server is off","timeStamp":"2018-01-02T18:08:33.562Z"}
{"level":"info","message":"Server is linstening on port 7000","timeStamp":"2018-01-02T18:09:50.146Z"}
{"level":"info","message":"Processing : POST on : /block","timeStamp":"2018-01-02T18:09:50.196Z"}
{"level":"info","message":"Server is off","timeStamp":"2018-01-02T18:09:50.217Z"}
{"level":"info","message":"Server is linstening on port 7000","timeStamp":"2018-01-02T18:10:27.702Z"}
{"level":"info","message":"Processing : POST on : /block","timeStamp":"2018-01-02T18:10:27.717Z"}
{"level":"info","message":"Server is off","timeStamp":"2018-01-02T18:10:27.738Z"}
{"level":"info","message":"Server is linstening on port 7000","timeStamp":"2018-01-02T18:10:41.576Z"}
{"level":"info","message":"Processing : POST on : /block","timeStamp":"2018-01-02T18:10:41.625Z"}
{"level":"info","message":"Server is off","timeStamp":"2018-01-02T18:10:41.645Z"}
{"level":"info","message":"Server is linstening on port 7000","timeStamp":"2018-01-02T18:12:53.785Z"}
{"level":"info","message":"Processing : POST on : /block","timeStamp":"2018-01-02T18:12:53.800Z"}
{"level":"info","message":"Server is off","timeStamp":"2018-01-02T18:12:53.821Z"}
{"level":"info","message":"Server is linstening on port 7000","timeStamp":"2018-01-02T18:14:21.274Z"}
{"level":"info","message":"Server is off","timeStamp":"2018-01-02T18:14:21.276Z"}
{"level":"info","message":"Server is linstening on port 7000","timeStamp":"2018-01-02T18:15:57.491Z"}
{"level":"info","message":"Server is off","timeStamp":"2018-01-02T18:15:57.492Z"}
{"level":"info","message":"Server is linstening on port 7000","timeStamp":"2018-01-02T18:16:07.070Z"}
{"level":"info","message":"Processing : POST on : /block","timeStamp":"2018-01-02T18:16:07.085Z"}
{"level":"info","message":"Server is off","timeStamp":"2018-01-02T18:16:07.105Z"}
{"level":"info","message":"Server is linstening on port 7000","timeStamp":"2018-01-02T18:18:00.831Z"}
{"level":"info","message":"Processing : POST on : /block","timeStamp":"2018-01-02T18:18:00.848Z"}
{"level":"info","message":"Server is off","timeStamp":"2018-01-02T18:18:00.869Z"}
{"level":"info","message":"Server is linstening on port 7000","timeStamp":"2018-01-02T18:18:30.043Z"}
{"level":"info","message":"Processing : POST on : /block","timeStamp":"2018-01-02T18:18:30.059Z"}
{"level":"info","message":"Server is off","timeStamp":"2018-01-02T18:18:30.078Z"}
{"level":"info","message":"Server is linstening on port 7000","timeStamp":"2018-01-02T18:19:11.585Z"}
{"level":"info","message":"Processing : POST on : /block","timeStamp":"2018-01-02T18:19:11.600Z"}
{"level":"info","message":"Server is off","timeStamp":"2018-01-02T18:19:11.619Z"}
{"level":"info","message":"Server is linstening on port 7000","timeStamp":"2018-01-02T18:19:25.266Z"}
{"level":"info","message":"Processing : POST on : /block","timeStamp":"2018-01-02T18:19:25.283Z"}
{"level":"info","message":"Server is off","timeStamp":"2018-01-02T18:19:25.303Z"}
{"level":"info","message":"Server is linstening on port 7000","timeStamp":"2018-01-02T18:21:07.342Z"}
{"level":"info","message":"Processing : POST on : /block","timeStamp":"2018-01-02T18:21:07.359Z"}
{"level":"info","message":"Server is off","timeStamp":"2018-01-02T18:21:07.382Z"}
{"level":"info","message":"Server is linstening on port 7000","timeStamp":"2018-01-02T18:21:23.780Z"}
{"level":"info","message":"Processing : POST on : /block","timeStamp":"2018-01-02T18:21:23.829Z"}
{"level":"info","message":"Server is off","timeStamp":"2018-01-02T18:21:23.850Z"}
{"level":"info","message":"Server is linstening on port 7000","timeStamp":"2018-01-02T18:22:00.556Z"}
{"level":"info","message":"Processing : POST on : /block","timeStamp":"2018-01-02T18:22:00.571Z"}
{"level":"info","message":"Server is off","timeStamp":"2018-01-02T18:22:00.591Z"}
{"level":"info","message":"Server is linstening on port 7000","timeStamp":"2018-01-02T18:22:37.733Z"}
{"level":"info","message":"Processing : POST on : /block","timeStamp":"2018-01-02T18:22:37.747Z"}
{"level":"info","message":"Server is off","timeStamp":"2018-01-02T18:22:37.767Z"}
{"level":"info","message":"Server is linstening on port 7000","timeStamp":"2018-01-02T18:25:39.531Z"}
{"level":"info","message":"Processing : POST on : /block","timeStamp":"2018-01-02T18:25:39.546Z"}
{"level":"info","message":"Server is off","timeStamp":"2018-01-02T18:25:39.565Z"}
{"level":"info","message":"Server is linstening on port 7000","timeStamp":"2018-01-02T18:26:02.318Z"}
{"level":"info","message":"Processing : POST on : /block","timeStamp":"2018-01-02T18:26:02.334Z"}
{"level":"info","message":"Server is off","timeStamp":"2018-01-02T18:26:02.356Z"}
{"level":"info","message":"Server is linstening on port 7000","timeStamp":"2018-01-02T18:28:57.221Z"}
{"level":"info","message":"Processing : POST on : /block","timeStamp":"2018-01-02T18:28:57.235Z"}
{"level":"info","message":"Server is off","timeStamp":"2018-01-02T18:28:57.261Z"}
{"level":"info","message":"Server is linstening on port 7000","timeStamp":"2018-01-02T18:29:13.408Z"}
{"level":"info","message":"Processing : POST on : /block","timeStamp":"2018-01-02T18:29:13.423Z"}
{"level":"info","message":"Server is off","timeStamp":"2018-01-02T18:29:13.441Z"}
{"level":"info","message":"Server is linstening on port 7000","timeStamp":"2018-01-02T18:29:22.479Z"}
{"level":"info","message":"Processing : POST on : /block","timeStamp":"2018-01-02T18:29:22.495Z"}
{"level":"info","message":"Server is off","timeStamp":"2018-01-02T18:29:22.514Z"}
{"level":"info","message":"Server is linstening on port 7000","timeStamp":"2018-01-02T18:29:31.292Z"}
{"level":"info","message":"Processing : POST on : /block","timeStamp":"2018-01-02T18:29:31.307Z"}
{"level":"info","message":"Server is off","timeStamp":"2018-01-02T18:29:31.331Z"}
{"level":"info","message":"Server is linstening on port 7000","timeStamp":"2018-01-02T18:29:39.994Z"}
{"level":"info","message":"Processing : POST on : /block","timeStamp":"2018-01-02T18:29:40.009Z"}
{"level":"info","message":"Server is off","timeStamp":"2018-01-02T18:29:40.029Z"}
{"level":"info","message":"Server is linstening on port 7000","timeStamp":"2018-01-02T18:29:58.897Z"}
{"level":"info","message":"Processing : POST on : /block","timeStamp":"2018-01-02T18:29:58.916Z"}
{"level":"info","message":"Server is off","timeStamp":"2018-01-02T18:29:58.935Z"}
{"level":"info","message":"Server is linstening on port 7000","timeStamp":"2018-01-02T18:33:16.957Z"}
{"level":"info","message":"Processing : POST on : /block","timeStamp":"2018-01-02T18:33:16.972Z"}
{"level":"info","message":"Server is off","timeStamp":"2018-01-02T18:33:16.992Z"}
{"level":"info","message":"Server is linstening on port 7000","timeStamp":"2018-01-02T18:34:21.429Z"}
{"level":"info","message":"Processing : POST on : /block","timeStamp":"2018-01-02T18:34:21.442Z"}
{"level":"info","message":"Server is off","timeStamp":"2018-01-02T18:34:21.463Z"}
{"level":"info","message":"Server is linstening on port 7000","timeStamp":"2018-01-02T18:34:51.284Z"}
{"level":"info","message":"Processing : POST on : /block","timeStamp":"2018-01-02T18:34:51.333Z"}
{"level":"info","message":"Server is off","timeStamp":"2018-01-02T18:34:51.353Z"}
{"level":"info","message":"Server is linstening on port 7000","timeStamp":"2018-01-02T19:11:53.302Z"}
{"level":"info","message":"Processing : POST on : /block","timeStamp":"2018-01-02T19:11:53.317Z"}
{"level":"info","message":"Server is off","timeStamp":"2018-01-02T19:11:53.345Z"}
{"level":"info","message":"Server is linstening on port 7000","timeStamp":"2018-01-02T19:19:54.789Z"}
{"level":"info","message":"Processing : POST on : /block","timeStamp":"2018-01-02T19:19:54.805Z"}
{"level":"info","message":"Server is off","timeStamp":"2018-01-02T19:19:54.836Z"}
{"level":"info","message":"Server is linstening on port 7000","timeStamp":"2018-01-02T19:20:10.151Z"}
{"level":"info","message":"Processing : POST on : /block","timeStamp":"2018-01-02T19:20:10.166Z"}
{"level":"info","message":"Server is off","timeStamp":"2018-01-02T19:20:10.190Z"}
{"level":"info","message":"Server is linstening on port 7000","timeStamp":"2018-01-02T19:22:09.825Z"}
{"level":"info","message":"Processing : POST on : /block","timeStamp":"2018-01-02T19:22:09.840Z"}
{"level":"info","message":"Server is off","timeStamp":"2018-01-02T19:22:09.866Z"}
{"level":"info","message":"Server is linstening on port 7000","timeStamp":"2018-01-02T19:24:13.115Z"}
{"level":"info","message":"Processing : POST on : /block","timeStamp":"2018-01-02T19:24:13.130Z"}
{"level":"info","message":"Server is off","timeStamp":"2018-01-02T19:24:13.153Z"}
{"level":"info","message":"Server is linstening on port 7000","timeStamp":"2018-01-02T19:26:07.550Z"}
{"level":"info","message":"Processing : POST on : /block","timeStamp":"2018-01-02T19:26:07.564Z"}
{"level":"info","message":"Server is off","timeStamp":"2018-01-02T19:26:07.588Z"}
{"level":"info","message":"Server is linstening on port 7000","timeStamp":"2018-01-02T19:26:48.517Z"}
{"level":"info","message":"Processing : POST on : /block","timeStamp":"2018-01-02T19:26:48.531Z"}
{"level":"info","message":"Server is off","timeStamp":"2018-01-02T19:26:48.557Z"}
{"level":"info","message":"Server is linstening on port 7000","timeStamp":"2018-01-02T19:27:17.666Z"}
{"level":"info","message":"Processing : POST on : /block","timeStamp":"2018-01-02T19:27:17.681Z"}
{"level":"info","message":"Server is off","timeStamp":"2018-01-02T19:27:17.703Z"}
{"level":"info","message":"Server is linstening on port 7000","timeStamp":"2018-01-02T19:28:42.266Z"}
{"level":"info","message":"Processing : POST on : /block","timeStamp":"2018-01-02T19:28:42.280Z"}
{"level":"info","message":"Server is off","timeStamp":"2018-01-02T19:28:42.302Z"}
{"level":"info","message":"Server is linstening on port 7000","timeStamp":"2018-01-02T19:28:59.276Z"}
{"level":"info","message":"Processing : POST on : /block","timeStamp":"2018-01-02T19:28:59.294Z"}
{"level":"info","message":"Server is off","timeStamp":"2018-01-02T19:28:59.320Z"}
{"level":"info","message":"Server is linstening on port 7000","timeStamp":"2018-01-02T19:29:21.697Z"}
{"level":"info","message":"Processing : POST on : /block","timeStamp":"2018-01-02T19:29:21.712Z"}
{"level":"info","message":"Server is off","timeStamp":"2018-01-02T19:29:21.733Z"}
{"level":"info","message":"Server is linstening on port 7000","timeStamp":"2018-01-02T19:31:10.074Z"}
{"level":"info","message":"Processing : POST on : /block","timeStamp":"2018-01-02T19:31:10.089Z"}
{"level":"info","message":"Server is off","timeStamp":"2018-01-02T19:31:10.112Z"}
{"level":"info","message":"Server is linstening on port 7000","timeStamp":"2018-01-02T19:31:42.812Z"}
{"level":"info","message":"Processing : POST on : /block","timeStamp":"2018-01-02T19:31:42.826Z"}
{"level":"info","message":"Server is off","timeStamp":"2018-01-02T19:31:42.847Z"}
{"level":"info","message":"Server is linstening on port 7000","timeStamp":"2018-01-02T19:32:00.772Z"}
{"level":"info","message":"Processing : POST on : /block","timeStamp":"2018-01-02T19:32:00.788Z"}
{"level":"info","message":"Server is off","timeStamp":"2018-01-02T19:32:00.808Z"}
{"level":"info","message":"Server is linstening on port 7000","timeStamp":"2018-01-02T19:32:41.067Z"}
{"level":"info","message":"Processing : POST on : /block","timeStamp":"2018-01-02T19:32:41.081Z"}
{"level":"info","message":"Server is off","timeStamp":"2018-01-02T19:32:41.104Z"}
{"level":"info","message":"Server is linstening on port 7000","timeStamp":"2018-01-02T19:33:24.449Z"}
{"level":"info","message":"Processing : POST on : /block","timeStamp":"2018-01-02T19:33:24.466Z"}
{"level":"info","message":"Server is off","timeStamp":"2018-01-02T19:33:24.488Z"}
{"level":"info","message":"Server is linstening on port 7000","timeStamp":"2018-01-02T19:34:14.989Z"}
{"level":"info","message":"Processing : POST on : /block","timeStamp":"2018-01-02T19:34:15.004Z"}
{"level":"info","message":"Server is off","timeStamp":"2018-01-02T19:34:15.536Z"}
{"level":"info","message":"Server is linstening on port 7000","timeStamp":"2018-01-02T19:35:14.908Z"}
{"level":"info","message":"Processing : POST on : /block","timeStamp":"2018-01-02T19:35:14.923Z"}
{"level":"info","message":"Server is off","timeStamp":"2018-01-02T19:35:15.349Z"}
{"level":"info","message":"Server is linstening on port 7000","timeStamp":"2018-01-02T19:35:26.334Z"}
{"level":"info","message":"Processing : POST on : /block","timeStamp":"2018-01-02T19:35:26.382Z"}
{"level":"info","message":"Server is off","timeStamp":"2018-01-02T19:35:26.812Z"}
{"level":"info","message":"Server is linstening on port 7000","timeStamp":"2018-01-02T19:36:17.497Z"}
{"level":"info","message":"Processing : POST on : /block","timeStamp":"2018-01-02T19:36:17.510Z"}
{"level":"info","message":"Server is off","timeStamp":"2018-01-02T19:36:17.971Z"}
{"level":"info","message":"Server is linstening on port 7000","timeStamp":"2018-01-02T19:36:32.924Z"}
{"level":"info","message":"Processing : POST on : /block","timeStamp":"2018-01-02T19:36:32.938Z"}
{"level":"info","message":"Server is off","timeStamp":"2018-01-02T19:36:33.369Z"}
{"level":"info","message":"Server is linstening on port 7000","timeStamp":"2018-01-02T19:36:58.242Z"}
{"level":"info","message":"Processing : POST on : /block","timeStamp":"2018-01-02T19:36:58.257Z"}
{"level":"info","message":"Server is off","timeStamp":"2018-01-02T19:36:58.278Z"}
{"level":"info","message":"Server is linstening on port 7000","timeStamp":"2018-01-02T19:37:13.078Z"}
{"level":"info","message":"Processing : POST on : /block","timeStamp":"2018-01-02T19:37:13.136Z"}
{"level":"info","message":"Server is off","timeStamp":"2018-01-02T19:37:13.560Z"}
{"level":"info","message":"Server is linstening on port 7000","timeStamp":"2018-01-02T22:28:08.868Z"}
{"level":"info","message":"Processing : POST on : /block","timeStamp":"2018-01-02T22:28:08.878Z"}
{"level":"info","message":"Server is off","timeStamp":"2018-01-02T22:28:09.606Z"}
{"level":"info","message":"Server is linstening on port 7000","timeStamp":"2018-01-02T22:34:32.394Z"}
{"level":"info","message":"Server is off","timeStamp":"2018-01-02T22:34:32.396Z"}
{"level":"info","message":"Server is linstening on port 7000","timeStamp":"2018-01-02T22:35:14.380Z"}
{"level":"info","message":"Server is off","timeStamp":"2018-01-02T22:35:14.382Z"}
{"level":"info","message":"Server is linstening on port 7000","timeStamp":"2018-01-02T22:35:27.594Z"}
{"level":"info","message":"Processing : POST on : /block","timeStamp":"2018-01-02T22:35:27.604Z"}
{"level":"info","message":"Server is off","timeStamp":"2018-01-02T22:35:28.101Z"}
{"level":"info","message":"Server is linstening on port 7000","timeStamp":"2018-01-02T22:35:53.372Z"}
{"level":"info","message":"Server is off","timeStamp":"2018-01-02T22:35:53.375Z"}
{"level":"info","message":"Server is linstening on port 7000","timeStamp":"2018-01-02T22:36:16.567Z"}
{"level":"info","message":"Server is off","timeStamp":"2018-01-02T22:36:16.569Z"}
{"level":"info","message":"Server is linstening on port 7000","timeStamp":"2018-01-02T22:37:16.672Z"}
{"level":"info","message":"Server is off","timeStamp":"2018-01-02T22:37:16.675Z"}
{"level":"info","message":"Server is linstening on port 7000","timeStamp":"2018-01-02T22:38:24.429Z"}
{"level":"info","message":"Processing : POST on : /block","timeStamp":"2018-01-02T22:38:24.439Z"}
{"level":"info","message":"Server is off","timeStamp":"2018-01-02T22:38:24.978Z"}
{"level":"info","message":"Server is linstening on port 7000","timeStamp":"2018-01-02T22:40:57.176Z"}
{"level":"info","message":"Processing : POST on : /block","timeStamp":"2018-01-02T22:40:57.186Z"}
{"level":"info","message":"Server is off","timeStamp":"2018-01-02T22:40:57.725Z"}
{"level":"info","message":"Server is linstening on port 7000","timeStamp":"2018-01-02T22:43:29.062Z"}
{"level":"info","message":"Processing : POST on : /block","timeStamp":"2018-01-02T22:43:29.073Z"}
{"level":"info","message":"Server is off","timeStamp":"2018-01-02T22:43:29.088Z"}
{"level":"info","message":"Server is linstening on port 7000","timeStamp":"2018-01-02T22:44:22.282Z"}
{"level":"info","message":"Processing : POST on : /block","timeStamp":"2018-01-02T22:44:22.292Z"}
{"level":"info","message":"Server is off","timeStamp":"2018-01-02T22:44:22.308Z"}
{"level":"info","message":"Server is linstening on port 7000","timeStamp":"2018-01-02T22:45:38.105Z"}
{"level":"info","message":"Processing : POST on : /block","timeStamp":"2018-01-02T22:45:38.116Z"}
{"level":"info","message":"Server is off","timeStamp":"2018-01-02T22:45:38.131Z"}
{"level":"info","message":"Server is linstening on port 7000","timeStamp":"2018-01-02T22:46:27.993Z"}
{"level":"info","message":"Processing : POST on : /block","timeStamp":"2018-01-02T22:46:28.004Z"}
{"level":"info","message":"Server is off","timeStamp":"2018-01-02T22:46:28.019Z"}
{"level":"info","message":"Server is linstening on port 7000","timeStamp":"2018-01-02T22:47:18.426Z"}
{"level":"info","message":"Processing : POST on : /block","timeStamp":"2018-01-02T22:47:18.438Z"}
{"level":"info","message":"Server is off","timeStamp":"2018-01-02T22:47:18.454Z"}
{"level":"info","message":"Server is linstening on port 7000","timeStamp":"2018-01-02T22:51:25.155Z"}
{"level":"info","message":"Processing : POST on : /block","timeStamp":"2018-01-02T22:51:25.166Z"}
{"level":"info","message":"Server is off","timeStamp":"2018-01-02T22:51:25.182Z"}
{"level":"info","message":"Server is linstening on port 7000","timeStamp":"2018-01-02T22:54:37.216Z"}
{"level":"info","message":"Processing : POST on : /block","timeStamp":"2018-01-02T22:54:37.226Z"}
{"level":"info","message":"Server is off","timeStamp":"2018-01-02T22:54:37.242Z"}
{"level":"info","message":"Server is linstening on port 7000","timeStamp":"2018-01-02T22:56:22.283Z"}
{"level":"info","message":"Processing : POST on : /block","timeStamp":"2018-01-02T22:56:22.293Z"}
{"level":"info","message":"Server is off","timeStamp":"2018-01-02T22:56:22.308Z"}
{"level":"info","message":"Server is linstening on port 7000","timeStamp":"2018-01-02T22:56:39.307Z"}
{"level":"info","message":"Processing : POST on : /block","timeStamp":"2018-01-02T22:56:39.320Z"}
{"level":"info","message":"Server is off","timeStamp":"2018-01-02T22:56:39.335Z"}
{"level":"info","message":"Server is linstening on port 7000","timestamp":"2018-01-02T22:57:27.438Z"}
{"level":"info","message":"Processing : POST on : /block","timestamp":"2018-01-02T22:57:27.451Z"}
{"level":"info","message":"Server is off","timestamp":"2018-01-02T22:57:27.465Z"}
{"level":"info","message":"Server is linstening on port 7000","timestamp":"2018-01-02T22:57:45.462Z"}
{"level":"info","message":"Processing : POST on : /block","timestamp":"2018-01-02T22:57:45.475Z"}
{"level":"info","message":"Server is off","timestamp":"2018-01-02T22:57:45.490Z"}
{"level":"info","message":"Server is linstening on port 7000","timestamp":"2018-01-02T23:00:20.102Z"}
{"level":"info","message":"Processing : POST on : /block","timestamp":"2018-01-02T23:00:20.113Z"}
{"level":"info","message":"Server is off","timestamp":"2018-01-02T23:00:20.129Z"}
{"level":"info","message":"Server is linstening on port 7000","timestamp":"2018-01-02T23:00:52.047Z"}
{"level":"info","message":"Processing : POST on : /block","timestamp":"2018-01-02T23:00:52.058Z"}
{"level":"info","message":"Server is off","timestamp":"2018-01-02T23:00:52.073Z"}
{"level":"info","message":"Server is linstening on port 7000","timestamp":"2018-01-02T23:01:26.433Z"}
{"level":"info","message":"Processing : POST on : /block","timestamp":"2018-01-02T23:01:26.446Z"}
{"level":"info","message":"Server is off","timestamp":"2018-01-02T23:01:26.461Z"}
{"level":"info","message":"Server is linstening on port 7000","timestamp":"2018-01-02T23:02:48.591Z"}
{"level":"info","message":"Processing : POST on : /block","timestamp":"2018-01-02T23:02:48.602Z"}
{"level":"info","message":"Server is off","timestamp":"2018-01-02T23:02:48.616Z"}
{"level":"info","message":"Server is linstening on port 7000","timestamp":"2018-01-02T23:04:25.595Z"}
{"level":"info","message":"Processing : POST on : /block","timestamp":"2018-01-02T23:04:25.605Z"}
{"level":"info","message":"Server is off","timestamp":"2018-01-02T23:04:26.177Z"}
{"level":"info","message":"Server is linstening on port 7000","timestamp":"2018-01-02T23:05:03.580Z"}
{"level":"info","message":"Processing : POST on : /block","timestamp":"2018-01-02T23:05:03.591Z"}
{"level":"info","message":"Server is off","timestamp":"2018-01-02T23:05:04.089Z"}
{"level":"info","message":"Server is linstening on port 7000","timestamp":"2018-01-02T23:12:24.776Z"}
{"level":"info","message":"Processing : POST on : /block","timestamp":"2018-01-02T23:12:24.787Z"}
{"level":"info","message":"Server is off","timestamp":"2018-01-02T23:12:25.361Z"}
{"level":"info","message":"Server is linstening on port 7000","timestamp":"2018-01-02T23:13:14.464Z"}
{"level":"info","message":"Processing : POST on : /block","timestamp":"2018-01-02T23:13:14.475Z"}
{"level":"info","message":"Server is off","timestamp":"2018-01-02T23:13:15.857Z"}
{"level":"info","message":"Server is linstening on port 7000","timestamp":"2018-01-02T23:13:33.435Z"}
{"level":"info","message":"Processing : POST on : /block","timestamp":"2018-01-02T23:13:33.446Z"}
{"level":"info","message":"Server is off","timestamp":"2018-01-02T23:13:33.947Z"}
{"level":"info","message":"Server is linstening on port 7000","timestamp":"2018-01-02T23:41:12.791Z"}
{"level":"info","message":"Processing : POST on : /block","timestamp":"2018-01-02T23:41:12.801Z"}
{"level":"info","message":"Server is off","timestamp":"2018-01-02T23:41:14.045Z"}
{"level":"info","message":"Server is linstening on port 7000","timestamp":"2018-01-02T23:41:35.078Z"}
{"level":"info","message":"Processing : POST on : /block","timestamp":"2018-01-02T23:41:35.088Z"}
{"level":"info","message":"Processing : POST on : /block","timestamp":"2018-01-02T23:41:35.815Z"}
{"level":"info","message":"Processing : POST on : /block","timestamp":"2018-01-02T23:41:35.912Z"}
{"level":"info","message":"Processing : POST on : /block","timestamp":"2018-01-02T23:41:36.101Z"}
{"level":"info","message":"Processing : POST on : /block","timestamp":"2018-01-02T23:41:36.298Z"}
{"level":"info","message":"Processing : POST on : /block","timestamp":"2018-01-02T23:41:36.377Z"}
{"level":"info","message":"Server is off","timestamp":"2018-01-02T23:41:36.499Z"}
{"level":"info","message":"Server is linstening on port 7000","timestamp":"2018-01-02T23:42:41.674Z"}
{"level":"info","message":"Processing : POST on : /block","timestamp":"2018-01-02T23:42:41.688Z"}
{"level":"info","message":"Processing : POST on : /block","timestamp":"2018-01-02T23:42:42.244Z"}
{"level":"info","message":"Processing : POST on : /block","timestamp":"2018-01-02T23:42:42.328Z"}
{"level":"info","message":"Server is off","timestamp":"2018-01-02T23:42:42.338Z"}
{"level":"info","message":"Server is linstening on port 7000","timestamp":"2018-01-02T23:43:18.603Z"}
{"level":"info","message":"Processing : POST on : /block","timestamp":"2018-01-02T23:43:18.614Z"}
{"level":"info","message":"Processing : POST on : /block","timestamp":"2018-01-02T23:43:19.148Z"}
{"level":"info","message":"Processing : POST on : /block","timestamp":"2018-01-02T23:43:19.232Z"}
{"level":"info","message":"Server is off","timestamp":"2018-01-02T23:43:19.240Z"}
{"level":"info","message":"Server is linstening on port 7000","timestamp":"2018-01-02T23:44:26.408Z"}
{"level":"info","message":"Processing : POST on : /block","timestamp":"2018-01-02T23:44:26.420Z"}
{"level":"info","message":"Processing : POST on : /block","timestamp":"2018-01-02T23:44:26.914Z"}
{"level":"info","message":"Processing : POST on : /block","timestamp":"2018-01-02T23:44:27.000Z"}
{"level":"info","message":"Server is off","timestamp":"2018-01-02T23:44:27.018Z"}
{"level":"info","message":"Server is linstening on port 7000","timestamp":"2018-01-02T23:46:25.798Z"}
{"level":"info","message":"Processing : POST on : /block","timestamp":"2018-01-02T23:46:25.808Z"}
{"level":"info","message":"Processing : POST on : /block","timestamp":"2018-01-02T23:46:26.347Z"}
{"level":"info","message":"Processing : POST on : /block","timestamp":"2018-01-02T23:46:26.433Z"}
{"level":"info","message":"Server is off","timestamp":"2018-01-02T23:46:26.448Z"}
{"level":"info","message":"Server is linstening on port 7000","timestamp":"2018-01-02T23:48:11.041Z"}
{"level":"info","message":"Processing : POST on : /block","timestamp":"2018-01-02T23:48:11.053Z"}
{"level":"info","message":"Processing : POST on : /block","timestamp":"2018-01-02T23:48:11.595Z"}
{"level":"info","message":"Processing : POST on : /block","timestamp":"2018-01-02T23:48:11.674Z"}
{"level":"info","message":"Server is off","timestamp":"2018-01-02T23:48:11.682Z"}
{"level":"info","message":"Server is linstening on port 7000","timestamp":"2018-01-02T23:48:31.665Z"}
{"level":"info","message":"Processing : POST on : /block","timestamp":"2018-01-02T23:48:31.679Z"}
{"level":"info","message":"Processing : POST on : /block","timestamp":"2018-01-02T23:48:32.216Z"}
{"level":"info","message":"Processing : POST on : /block","timestamp":"2018-01-02T23:48:32.328Z"}
{"level":"info","message":"Server is off","timestamp":"2018-01-02T23:48:32.333Z"}
{"level":"info","message":"Server is linstening on port 7000","timestamp":"2018-01-02T23:49:55.623Z"}
{"level":"info","message":"Processing : POST on : /block","timestamp":"2018-01-02T23:49:55.633Z"}
{"level":"info","message":"Processing : POST on : /block","timestamp":"2018-01-02T23:49:56.191Z"}
{"level":"info","message":"Processing : POST on : /block","timestamp":"2018-01-02T23:49:56.274Z"}
{"level":"info","message":"Server is off","timestamp":"2018-01-02T23:49:56.292Z"}
{"level":"info","message":"Server is linstening on port 7000","timestamp":"2018-01-02T23:55:17.876Z"}
{"level":"info","message":"Processing : POST on : /block","timestamp":"2018-01-02T23:55:17.886Z"}
{"level":"info","message":"Processing : POST on : /block","timestamp":"2018-01-02T23:55:18.505Z"}
{"level":"info","message":"Server is off","timestamp":"2018-01-02T23:55:18.587Z"}
{"level":"info","message":"Server is linstening on port 7000","timestamp":"2018-01-02T23:55:51.546Z"}
{"level":"info","message":"Processing : POST on : /block","timestamp":"2018-01-02T23:55:51.557Z"}
{"level":"info","message":"Processing : POST on : /block","timestamp":"2018-01-02T23:55:52.068Z"}
{"level":"info","message":"Processing : POST on : /block","timestamp":"2018-01-02T23:55:52.152Z"}
{"level":"info","message":"Server is off","timestamp":"2018-01-02T23:55:52.166Z"}
{"level":"info","message":"Server is linstening on port 7000","timestamp":"2018-01-02T23:56:07.984Z"}
{"level":"info","message":"Processing : POST on : /block","timestamp":"2018-01-02T23:56:07.997Z"}
{"level":"info","message":"Processing : POST on : /block","timestamp":"2018-01-02T23:56:08.478Z"}
{"level":"info","message":"Processing : POST on : /block","timestamp":"2018-01-02T23:56:08.560Z"}
{"level":"info","message":"Processing : POST on : /block","timestamp":"2018-01-02T23:56:08.638Z"}
{"level":"info","message":"Processing : POST on : /block","timestamp":"2018-01-02T23:56:08.734Z"}
{"level":"info","message":"Server is off","timestamp":"2018-01-02T23:56:08.822Z"}
{"level":"info","message":"Server is linstening on port 7000","timestamp":"2018-01-02T23:57:38.921Z"}
{"level":"info","message":"Processing : POST on : /block","timestamp":"2018-01-02T23:57:38.931Z"}
{"level":"info","message":"Server is off","timestamp":"2018-01-02T23:57:39.483Z"}
{"level":"info","message":"Server is linstening on port 7000","timestamp":"2018-01-02T23:57:39.491Z"}
{"level":"info","message":"Processing : POST on : /block","timestamp":"2018-01-02T23:57:39.497Z"}
{"level":"info","message":"Processing : POST on : /block","timestamp":"2018-01-02T23:57:39.949Z"}
{"level":"info","message":"Server is off","timestamp":"2018-01-02T23:57:39.961Z"}
{"level":"info","message":"Server is linstening on port 7000","timestamp":"2018-01-02T23:58:33.273Z"}
{"level":"info","message":"Processing : POST on : /block","timestamp":"2018-01-02T23:58:33.289Z"}
{"level":"info","message":"Processing : POST on : /block","timestamp":"2018-01-02T23:58:33.804Z"}
{"level":"info","message":"Processing : POST on : /block","timestamp":"2018-01-02T23:58:33.891Z"}
{"level":"info","message":"Processing : POST on : /block","timestamp":"2018-01-02T23:58:33.972Z"}
{"level":"info","message":"Processing : POST on : /block","timestamp":"2018-01-02T23:58:34.071Z"}
{"level":"info","message":"Server is off","timestamp":"2018-01-02T23:58:34.156Z"}
{"level":"info","message":"Server is linstening on port 7000","timestamp":"2018-01-03T00:00:08.123Z"}
{"level":"info","message":"Processing : POST on : /socket","timestamp":"2018-01-03T00:00:08.149Z"}
{"level":"info","message":"Processing : POST on : /socket","timestamp":"2018-01-03T00:00:08.768Z"}
{"level":"info","message":"Processing : GET on : /socket","timestamp":"2018-01-03T00:00:08.848Z"}
{"level":"info","message":"Server is off","timestamp":"2018-01-03T00:00:09.026Z"}
{"level":"info","message":"Server is linstening on port 7000","timestamp":"2018-01-03T00:00:09.484Z"}
{"level":"info","message":"Processing : POST on : /block","timestamp":"2018-01-03T00:00:09.533Z"}
{"level":"info","message":"Processing : POST on : /block","timestamp":"2018-01-03T00:00:09.947Z"}
{"level":"info","message":"Processing : POST on : /block","timestamp":"2018-01-03T00:00:10.037Z"}
{"level":"info","message":"Processing : POST on : /block","timestamp":"2018-01-03T00:00:10.115Z"}
{"level":"info","message":"Processing : POST on : /block","timestamp":"2018-01-03T00:00:10.194Z"}
{"level":"info","message":"Server is off","timestamp":"2018-01-03T00:00:10.273Z"}
{"level":"info","message":"Server is linstening on port 7000","timestamp":"2018-01-03T00:39:39.702Z"}
{"level":"info","message":"Processing : POST on : /socket","timestamp":"2018-01-03T00:39:39.717Z"}
{"level":"info","message":"Processing : POST on : /socket","timestamp":"2018-01-03T00:39:40.255Z"}
{"level":"info","message":"Processing : GET on : /socket","timestamp":"2018-01-03T00:39:40.326Z"}
{"level":"info","message":"Server is off","timestamp":"2018-01-03T00:39:40.469Z"}
{"level":"info","message":"Server is linstening on port 7000","timestamp":"2018-01-03T00:39:41.585Z"}
{"level":"info","message":"Processing : GET on : /chain","timestamp":"2018-01-03T00:39:41.649Z"}
{"level":"info","message":"Returning a 404 from the catch all route.","timestamp":"2018-01-03T00:39:41.650Z"}
{"level":"info","message":"Server is off","timestamp":"2018-01-03T00:39:41.655Z"}
{"level":"info","message":"Server is linstening on port 7000","timestamp":"2018-01-03T00:39:42.273Z"}
{"level":"info","message":"Processing : POST on : /block","timestamp":"2018-01-03T00:39:42.359Z"}
{"level":"info","message":"Processing : POST on : /block","timestamp":"2018-01-03T00:39:42.767Z"}
{"level":"info","message":"Processing : POST on : /block","timestamp":"2018-01-03T00:39:42.839Z"}
{"level":"info","message":"Processing : POST on : /block","timestamp":"2018-01-03T00:39:42.907Z"}
{"level":"info","message":"Processing : POST on : /block","timestamp":"2018-01-03T00:39:42.977Z"}
{"level":"info","message":"Server is off","timestamp":"2018-01-03T00:39:43.046Z"}
{"level":"info","message":"Server is linstening on port 7000","timestamp":"2018-01-03T00:39:58.621Z"}
{"level":"info","message":"Processing : POST on : /block","timestamp":"2018-01-03T00:39:58.637Z"}
{"level":"info","message":"Processing : POST on : /block","timestamp":"2018-01-03T00:39:59.062Z"}
{"level":"info","message":"Processing : POST on : /block","timestamp":"2018-01-03T00:39:59.135Z"}
{"level":"info","message":"Processing : POST on : /block","timestamp":"2018-01-03T00:39:59.204Z"}
{"level":"info","message":"Processing : POST on : /block","timestamp":"2018-01-03T00:39:59.275Z"}
{"level":"info","message":"Server is off","timestamp":"2018-01-03T00:39:59.347Z"}
{"level":"info","message":"Server is linstening on port 7000","timestamp":"2018-01-03T00:40:22.953Z"}
{"level":"info","message":"Processing : GET on : /chain","timestamp":"2018-01-03T00:40:22.971Z"}
{"level":"info","message":"Returning a 404 from the catch all route.","timestamp":"2018-01-03T00:40:22.972Z"}
{"level":"info","message":"Server is off","timestamp":"2018-01-03T00:40:22.980Z"}
{"level":"info","message":"Server is linstening on port 7000","timestamp":"2018-01-03T00:41:30.038Z"}
{"level":"info","message":"Processing : GET on : /chain","timestamp":"2018-01-03T00:41:30.050Z"}
{"level":"info","message":"Server is off","timestamp":"2018-01-03T00:41:30.510Z"}
{"level":"info","message":"Server is linstening on port 7000","timestamp":"2018-01-03T00:42:23.268Z"}
{"level":"info","message":"Processing : GET on : /chain","timestamp":"2018-01-03T00:42:23.282Z"}
{"level":"info","message":"Server is off","timestamp":"2018-01-03T00:42:23.722Z"}
{"level":"info","message":"Server is linstening on port 7000","timestamp":"2018-01-03T00:43:02.310Z"}
{"level":"info","message":"Processing : GET on : /chain","timestamp":"2018-01-03T00:43:02.323Z"}
{"level":"info","message":"Server is off","timestamp":"2018-01-03T00:43:02.787Z"}
{"level":"info","message":"Server is linstening on port 7000","timestamp":"2018-01-03T00:43:37.629Z"}
{"level":"info","message":"Processing : GET on : /chain","timestamp":"2018-01-03T00:43:37.642Z"}
{"level":"info","message":"Server is off","timestamp":"2018-01-03T00:43:38.149Z"}
{"level":"info","message":"Server is linstening on port 7000","timestamp":"2018-01-03T00:44:16.201Z"}
{"level":"info","message":"Processing : GET on : /chain","timestamp":"2018-01-03T00:44:16.215Z"}
{"level":"info","message":"Server is off","timestamp":"2018-01-03T00:44:16.224Z"}
{"level":"info","message":"Server is linstening on port 7000","timestamp":"2018-01-03T00:44:35.724Z"}
{"level":"info","message":"Processing : GET on : /chain","timestamp":"2018-01-03T00:44:35.737Z"}
{"level":"info","message":"Server is off","timestamp":"2018-01-03T00:44:35.751Z"}
{"level":"info","message":"Server is linstening on port 7000","timestamp":"2018-01-03T00:45:23.573Z"}
{"level":"info","message":"Processing : GET on : /chain","timestamp":"2018-01-03T00:45:23.586Z"}
{"level":"info","message":"Server is off","timestamp":"2018-01-03T00:45:24.098Z"}
{"level":"info","message":"Server is linstening on port 7000","timestamp":"2018-01-03T00:45:31.287Z"}
{"level":"info","message":"Processing : GET on : /chain","timestamp":"2018-01-03T00:45:31.301Z"}
{"level":"info","message":"Server is off","timestamp":"2018-01-03T00:45:31.807Z"}
{"level":"info","message":"Server is linstening on port 7000","timestamp":"2018-01-03T00:47:55.381Z"}
{"level":"info","message":"Processing : GET on : /chain","timestamp":"2018-01-03T00:47:55.394Z"}
{"level":"info","message":"Server is off","timestamp":"2018-01-03T00:47:55.923Z"}
{"level":"info","message":"Server is linstening on port 7000","timestamp":"2018-01-03T00:48:16.380Z"}
{"level":"info","message":"Processing : GET on : /chain","timestamp":"2018-01-03T00:48:16.393Z"}
{"level":"info","message":"Server is off","timestamp":"2018-01-03T00:48:16.918Z"}
{"level":"info","message":"Server is linstening on port 7000","timestamp":"2018-01-03T00:50:50.991Z"}
{"level":"info","message":"Processing : GET on : /chain","timestamp":"2018-01-03T00:50:51.005Z"}
{"level":"info","message":"Server is off","timestamp":"2018-01-03T00:50:51.487Z"}
{"level":"info","message":"Server is linstening on port 7000","timestamp":"2018-01-03T00:50:51.659Z"}
{"level":"info","message":"Processing : POST on : /block","timestamp":"2018-01-03T00:50:51.727Z"}
{"level":"info","message":"Processing : POST on : /block","timestamp":"2018-01-03T00:50:52.110Z"}
{"level":"info","message":"Processing : POST on : /block","timestamp":"2018-01-03T00:50:52.183Z"}
{"level":"info","message":"Processing : POST on : /block","timestamp":"2018-01-03T00:50:52.253Z"}
{"level":"info","message":"Processing : POST on : /block","timestamp":"2018-01-03T00:50:52.325Z"}
{"level":"info","message":"Server is off","timestamp":"2018-01-03T00:50:52.397Z"}
{"level":"info","message":"Server is linstening on port 7000","timestamp":"2018-01-03T00:51:52.435Z"}
{"level":"info","message":"Processing : GET on : /chain","timestamp":"2018-01-03T00:51:52.449Z"}
{"level":"info","message":"Server is off","timestamp":"2018-01-03T00:51:52.880Z"}
{"level":"info","message":"Server is linstening on port 7000","timestamp":"2018-01-03T00:51:53.033Z"}
{"level":"info","message":"Processing : POST on : /block","timestamp":"2018-01-03T00:51:53.038Z"}
{"level":"info","message":"Processing : POST on : /block","timestamp":"2018-01-03T00:51:53.455Z"}
{"level":"info","message":"Processing : POST on : /block","timestamp":"2018-01-03T00:51:53.527Z"}
{"level":"info","message":"Processing : POST on : /block","timestamp":"2018-01-03T00:51:53.596Z"}
{"level":"info","message":"Processing : POST on : /block","timestamp":"2018-01-03T00:51:53.666Z"}
{"level":"info","message":"Server is off","timestamp":"2018-01-03T00:51:53.734Z"}
{"level":"info","message":"Server is linstening on port 7000","timestamp":"2018-01-03T00:54:58.238Z"}
{"level":"info","message":"Processing : GET on : /chain","timestamp":"2018-01-03T00:54:58.251Z"}
{"level":"info","message":"Server is off","timestamp":"2018-01-03T00:54:58.703Z"}
{"level":"info","message":"Server is linstening on port 7000","timestamp":"2018-01-03T00:56:36.717Z"}
{"level":"info","message":"Processing : GET on : /chain","timestamp":"2018-01-03T00:56:36.730Z"}
{"level":"info","message":"Server is off","timestamp":"2018-01-03T00:56:37.218Z"}
{"level":"info","message":"Server is linstening on port 7000","timestamp":"2018-01-03T00:57:24.171Z"}
{"level":"info","message":"Processing : GET on : /chain","timestamp":"2018-01-03T00:57:24.186Z"}
{"level":"info","message":"Server is off","timestamp":"2018-01-03T00:57:24.623Z"}
{"level":"info","message":"Server is linstening on port 7000","timestamp":"2018-01-03T01:07:08.522Z"}
{"level":"info","message":"Processing : GET on : /chain","timestamp":"2018-01-03T01:07:08.535Z"}
{"level":"info","message":"Server is off","timestamp":"2018-01-03T01:07:08.996Z"}
{"level":"info","message":"Server is linstening on port 7000","timestamp":"2018-01-03T01:07:27.273Z"}
{"level":"info","message":"Processing : GET on : /chain","timestamp":"2018-01-03T01:07:27.287Z"}
{"level":"info","message":"Server is off","timestamp":"2018-01-03T01:07:27.722Z"}
{"level":"info","message":"Server is linstening on port 7000","timestamp":"2018-01-03T01:12:37.097Z"}
{"level":"info","message":"Processing : GET on : /chain","timestamp":"2018-01-03T01:12:37.121Z"}
{"level":"info","message":"Server is off","timestamp":"2018-01-03T01:12:37.588Z"}
{"level":"info","message":"Server is linstening on port 7000","timestamp":"2018-01-03T01:13:07.960Z"}
{"level":"info","message":"Processing : GET on : /chain","timestamp":"2018-01-03T01:13:07.985Z"}
{"level":"info","message":"Server is off","timestamp":"2018-01-03T01:13:08.428Z"}
{"level":"info","message":"Server is linstening on port 7000","timestamp":"2018-01-03T01:13:08.573Z"}
{"level":"info","message":"Processing : POST on : /block","timestamp":"2018-01-03T01:13:08.580Z"}
{"level":"info","message":"Processing : POST on : /block","timestamp":"2018-01-03T01:13:09.005Z"}
{"level":"info","message":"Processing : POST on : /block","timestamp":"2018-01-03T01:13:09.077Z"}
{"level":"info","message":"Processing : POST on : /block","timestamp":"2018-01-03T01:13:09.149Z"}
{"level":"info","message":"Processing : POST on : /block","timestamp":"2018-01-03T01:13:09.219Z"}
{"level":"info","message":"Server is off","timestamp":"2018-01-03T01:13:09.288Z"}
{"level":"info","message":"Server is linstening on port 7000","timestamp":"2018-01-03T01:13:21.743Z"}
{"level":"info","message":"Processing : GET on : /chain","timestamp":"2018-01-03T01:13:21.766Z"}
{"level":"info","message":"Server is off","timestamp":"2018-01-03T01:13:22.196Z"}
{"level":"info","message":"Server is linstening on port 7000","timestamp":"2018-01-03T01:13:22.337Z"}
{"level":"info","message":"Processing : POST on : /block","timestamp":"2018-01-03T01:13:22.345Z"}
{"level":"info","message":"Processing : POST on : /block","timestamp":"2018-01-03T01:13:24.061Z"}
{"level":"info","message":"Processing : POST on : /block","timestamp":"2018-01-03T01:13:24.133Z"}
{"level":"info","message":"Processing : POST on : /block","timestamp":"2018-01-03T01:13:24.203Z"}
{"level":"info","message":"Processing : POST on : /block","timestamp":"2018-01-03T01:13:24.276Z"}
{"level":"info","message":"Server is off","timestamp":"2018-01-03T01:13:24.345Z"}
{"level":"info","message":"Server is linstening on port 7000","timestamp":"2018-01-03T01:13:49.879Z"}
{"level":"info","message":"Processing : POST on : /block","timestamp":"2018-01-03T01:13:49.904Z"}
{"level":"info","message":"Processing : POST on : /block","timestamp":"2018-01-03T01:13:50.599Z"}
{"level":"info","message":"Processing : POST on : /block","timestamp":"2018-01-03T01:13:50.672Z"}
{"level":"info","message":"Processing : POST on : /block","timestamp":"2018-01-03T01:13:50.743Z"}
{"level":"info","message":"Processing : POST on : /block","timestamp":"2018-01-03T01:13:50.813Z"}
{"level":"info","message":"Server is off","timestamp":"2018-01-03T01:13:50.884Z"}
{"level":"info","message":"Server is linstening on port 7000","timestamp":"2018-01-03T01:13:51.029Z"}
{"level":"info","message":"Processing : GET on : /chain","timestamp":"2018-01-03T01:13:51.091Z"}
{"level":"info","message":"Server is off","timestamp":"2018-01-03T01:13:51.713Z"}
{"level":"info","message":"Server is linstening on port 7000","timestamp":"2018-01-03T01:14:19.443Z"}
{"level":"info","message":"Processing : POST on : /block","timestamp":"2018-01-03T01:14:19.469Z"}
{"level":"info","message":"Processing : POST on : /block","timestamp":"2018-01-03T01:14:20.200Z"}
{"level":"info","message":"Processing : POST on : /block","timestamp":"2018-01-03T01:14:20.276Z"}
{"level":"info","message":"Processing : POST on : /block","timestamp":"2018-01-03T01:14:20.347Z"}
{"level":"info","message":"Processing : POST on : /block","timestamp":"2018-01-03T01:14:20.418Z"}
{"level":"info","message":"Server is off","timestamp":"2018-01-03T01:14:20.489Z"}
{"level":"info","message":"Server is linstening on port 7000","timestamp":"2018-01-03T01:14:31.645Z"}
{"level":"info","message":"Processing : POST on : /block","timestamp":"2018-01-03T01:14:31.670Z"}
{"level":"info","message":"Processing : POST on : /block","timestamp":"2018-01-03T01:14:32.362Z"}
{"level":"info","message":"Processing : POST on : /block","timestamp":"2018-01-03T01:14:32.438Z"}
{"level":"info","message":"Processing : POST on : /block","timestamp":"2018-01-03T01:14:32.507Z"}
{"level":"info","message":"Processing : POST on : /block","timestamp":"2018-01-03T01:14:32.577Z"}
{"level":"info","message":"Server is off","timestamp":"2018-01-03T01:14:32.647Z"}
{"level":"info","message":"Server is linstening on port 7000","timestamp":"2018-01-03T01:16:19.352Z"}
{"level":"info","message":"Processing : GET on : /chain","timestamp":"2018-01-03T01:16:19.381Z"}
{"level":"info","message":"Server is off","timestamp":"2018-01-03T01:16:20.094Z"}
{"level":"info","message":"Server is linstening on port 7000","timestamp":"2018-01-03T01:16:36.884Z"}
{"level":"info","message":"Processing : GET on : /chain","timestamp":"2018-01-03T01:16:36.907Z"}
{"level":"info","message":"Server is off","timestamp":"2018-01-03T01:16:37.624Z"}
{"level":"info","message":"Server is linstening on port 7000","timestamp":"2018-01-03T01:35:17.596Z"}
{"level":"info","message":"Processing : POST on : /block","timestamp":"2018-01-03T01:35:17.620Z"}
{"level":"info","message":"Server is off","timestamp":"2018-01-03T01:35:17.640Z"}
{"level":"info","message":"Server is linstening on port 7000","timestamp":"2018-01-03T01:35:44.305Z"}
{"level":"info","message":"Processing : POST on : /block","timestamp":"2018-01-03T01:35:44.329Z"}
{"level":"info","message":"Server is off","timestamp":"2018-01-03T01:35:44.346Z"}
{"level":"info","message":"Server is linstening on port 7000","timestamp":"2018-01-03T01:36:26.917Z"}
{"level":"info","message":"Processing : POST on : /block","timestamp":"2018-01-03T01:36:26.941Z"}
{"level":"info","message":"Server is off","timestamp":"2018-01-03T01:36:26.965Z"}
{"level":"info","message":"Server is linstening on port 7000","timestamp":"2018-01-03T01:37:05.863Z"}
{"level":"info","message":"Processing : POST on : /block","timestamp":"2018-01-03T01:37:05.886Z"}
{"level":"info","message":"Server is off","timestamp":"2018-01-03T01:37:05.904Z"}
{"level":"info","message":"Server is linstening on port 7000","timestamp":"2018-01-03T01:37:36.597Z"}
{"level":"info","message":"Processing : POST on : /block","timestamp":"2018-01-03T01:37:36.622Z"}
{"level":"info","message":"Server is off","timestamp":"2018-01-03T01:37:36.641Z"}
{"level":"info","message":"Server is linstening on port 7000","timestamp":"2018-01-03T01:38:33.628Z"}
{"level":"info","message":"Processing : POST on : /block","timestamp":"2018-01-03T01:38:33.651Z"}
{"level":"info","message":"Processing : POST on : /block","timestamp":"2018-01-03T01:38:34.132Z"}
{"level":"info","message":"Processing : POST on : /block","timestamp":"2018-01-03T01:38:34.209Z"}
{"level":"info","message":"Processing : POST on : /block","timestamp":"2018-01-03T01:38:34.290Z"}
{"level":"info","message":"Processing : POST on : /block","timestamp":"2018-01-03T01:38:34.369Z"}
{"level":"info","message":"Server is off","timestamp":"2018-01-03T01:38:34.445Z"}
{"level":"info","message":"Server is linstening on port 7000","timestamp":"2018-01-03T01:43:34.165Z"}
{"level":"info","message":"Processing : POST on : /block","timestamp":"2018-01-03T01:43:34.193Z"}
{"level":"info","message":"Processing : POST on : /block","timestamp":"2018-01-03T01:43:36.080Z"}
{"level":"info","message":"Processing : POST on : /block","timestamp":"2018-01-03T01:43:36.210Z"}
{"level":"info","message":"Processing : POST on : /block","timestamp":"2018-01-03T01:43:36.290Z"}
{"level":"info","message":"Processing : POST on : /block","timestamp":"2018-01-03T01:43:36.419Z"}
{"level":"info","message":"Server is off","timestamp":"2018-01-03T01:43:36.499Z"}
{"level":"info","message":"Server is linstening on port 7000","timestamp":"2018-01-03T01:43:37.224Z"}
{"level":"info","message":"Processing : GET on : /chain","timestamp":"2018-01-03T01:43:37.289Z"}
{"level":"info","message":"Server is off","timestamp":"2018-01-03T01:43:37.744Z"}
{"level":"info","message":"Server is linstening on port 7000","timestamp":"2018-01-03T01:44:24.964Z"}
{"level":"info","message":"Processing : POST on : /socket","timestamp":"2018-01-03T01:44:24.985Z"}
{"level":"info","message":"Processing : POST on : /socket","timestamp":"2018-01-03T01:44:25.554Z"}
{"level":"info","message":"Processing : GET on : /socket","timestamp":"2018-01-03T01:44:25.635Z"}
{"level":"info","message":"Server is off","timestamp":"2018-01-03T01:44:25.800Z"}
{"level":"info","message":"Server is linstening on port 7000","timestamp":"2018-01-03T01:44:26.658Z"}
{"level":"info","message":"Processing : POST on : /block","timestamp":"2018-01-03T01:44:26.719Z"}
{"level":"info","message":"Processing : POST on : /block","timestamp":"2018-01-03T01:44:27.160Z"}
{"level":"info","message":"Processing : POST on : /block","timestamp":"2018-01-03T01:44:27.236Z"}
{"level":"info","message":"Server is off","timestamp":"2018-01-03T01:44:27.244Z"}
{"level":"info","message":"Server is linstening on port 7000","timestamp":"2018-01-03T01:44:27.470Z"}
{"level":"info","message":"Processing : GET on : /chain","timestamp":"2018-01-03T01:44:27.474Z"}
{"level":"info","message":"Server is off","timestamp":"2018-01-03T01:44:27.913Z"}
{"level":"info","message":"Server is linstening on port 7000","timestamp":"2018-01-03T03:00:40.944Z"}
{"level":"info","message":"Processing : POST on : /block","timestamp":"2018-01-03T03:00:40.966Z"}
{"level":"info","message":"Processing : POST on : /block","timestamp":"2018-01-03T03:00:41.480Z"}
{"level":"info","message":"Processing : POST on : /block","timestamp":"2018-01-03T03:00:41.557Z"}
{"level":"info","message":"Server is off","timestamp":"2018-01-03T03:00:41.564Z"}
{"level":"info","message":"Server is linstening on port 7000","timestamp":"2018-01-03T03:00:41.715Z"}
{"level":"info","message":"Processing : POST on : /socket","timestamp":"2018-01-03T03:00:41.784Z"}
{"level":"info","message":"Processing : POST on : /socket","timestamp":"2018-01-03T03:00:42.288Z"}
{"level":"info","message":"Processing : GET on : /socket","timestamp":"2018-01-03T03:00:42.363Z"}
{"level":"info","message":"Server is off","timestamp":"2018-01-03T03:00:42.512Z"}
{"level":"info","message":"Server is linstening on port 7000","timestamp":"2018-01-03T03:00:42.771Z"}
{"level":"info","message":"Processing : GET on : /chain","timestamp":"2018-01-03T03:00:42.774Z"}
{"level":"info","message":"Server is off","timestamp":"2018-01-03T03:00:43.199Z"}
{"level":"info","message":"Server is linstening on port 7000","timestamp":"2018-01-03T03:02:52.410Z"}
{"level":"info","message":"Processing : POST on : /block","timestamp":"2018-01-03T03:02:52.433Z"}
{"level":"info","message":"Processing : POST on : /block","timestamp":"2018-01-03T03:02:52.914Z"}
{"level":"info","message":"Processing : POST on : /block","timestamp":"2018-01-03T03:02:52.986Z"}
{"level":"info","message":"Processing : POST on : /block","timestamp":"2018-01-03T03:02:53.061Z"}
{"level":"info","message":"Processing : POST on : /block","timestamp":"2018-01-03T03:02:53.553Z"}
{"level":"info","message":"Server is off","timestamp":"2018-01-03T03:02:53.650Z"}
{"level":"info","message":"Server is linstening on port 7000","timestamp":"2018-01-03T03:02:53.783Z"}
{"level":"info","message":"Processing : POST on : /socket","timestamp":"2018-01-03T03:02:53.846Z"}
{"level":"info","message":"Processing : POST on : /socket","timestamp":"2018-01-03T03:02:54.370Z"}
{"level":"info","message":"Processing : GET on : /socket","timestamp":"2018-01-03T03:02:54.448Z"}
{"level":"info","message":"Server is off","timestamp":"2018-01-03T03:02:54.607Z"}
{"level":"info","message":"Server is linstening on port 7000","timestamp":"2018-01-03T03:02:54.913Z"}
{"level":"info","message":"Processing : GET on : /chain","timestamp":"2018-01-03T03:02:54.919Z"}
{"level":"info","message":"Server is off","timestamp":"2018-01-03T03:02:55.351Z"}
{"level":"info","message":"Server is linstening on port 7000","timestamp":"2018-01-03T03:03:37.654Z"}
{"level":"info","message":"Processing : POST on : /block","timestamp":"2018-01-03T03:03:37.678Z"}
{"level":"info","message":"Processing : POST on : /block","timestamp":"2018-01-03T03:03:38.124Z"}
{"level":"info","message":"Processing : POST on : /block","timestamp":"2018-01-03T03:03:38.202Z"}
{"level":"info","message":"Processing : POST on : /block","timestamp":"2018-01-03T03:03:38.278Z"}
{"level":"info","message":"Processing : POST on : /block","timestamp":"2018-01-03T03:03:38.349Z"}
{"level":"info","message":"Processing : POST on : /block","timestamp":"2018-01-03T03:03:38.431Z"}
{"level":"info","message":"Server is off","timestamp":"2018-01-03T03:03:38.501Z"}
{"level":"info","message":"Server is linstening on port 7000","timestamp":"2018-01-03T03:03:38.641Z"}
{"level":"info","message":"Processing : POST on : /socket","timestamp":"2018-01-03T03:03:38.705Z"}
{"level":"info","message":"Processing : POST on : /socket","timestamp":"2018-01-03T03:03:39.203Z"}
{"level":"info","message":"Processing : GET on : /socket","timestamp":"2018-01-03T03:03:39.274Z"}
{"level":"info","message":"Server is off","timestamp":"2018-01-03T03:03:39.419Z"}
{"level":"info","message":"Server is linstening on port 7000","timestamp":"2018-01-03T03:03:39.652Z"}
{"level":"info","message":"Processing : GET on : /chain","timestamp":"2018-01-03T03:03:39.655Z"}
{"level":"info","message":"Server is off","timestamp":"2018-01-03T03:03:40.104Z"}
